wandern/__init__.py
wandern/__main__.py
wandern/constants.py
wandern/exceptions.py
wandern/graph.py
wandern/migration.py
wandern/models.py
wandern/utils.py
wandern/agents/__init__.py
wandern/agents/base_agent.py
wandern/agents/constants.py
wandern/agents/migration_agent.py
wandern/agents/models.py
wandern/cli/__init__.py
wandern/cli/main.py
wandern/cli/utils.py
wandern/databases/__init__.py
wandern/databases/base.py
wandern/databases/postgresql.py
wandern/databases/provider.py
wandern/databases/sqlite.py
wandern/templates/__init__.py
wandern/templates/engine.py
wandern-0.0.3.dist-info/licenses/LICENSE
wandern-0.0.3.dist-info/METADATA
wandern-0.0.3.dist-info/WHEEL
wandern-0.0.3.dist-info/entry_points.txt
wandern-0.0.3.dist-info/top_level.txt
wandern-0.0.3.dist-info/RECORD
