Metadata-Version: 2.4
Name: wandern
Version: 0.0.3
Summary: Wandern is a small, no-nonsense database migration tool for python
Author-email: Shiladitya Bose <shiladitya_basu@live.com>
Project-URL: Homepage, https://github.com/s-bose/wandern
Project-URL: Issues, https://github.com/s-bose/wandern/issues
Classifier: Programming Language :: Python :: 3
Classifier: Operating System :: OS Independent
Classifier: License :: OSI Approved :: MIT License
Requires-Python: >=3.11
License-File: LICENSE
Requires-Dist: jinja2>=3.1.6
Requires-Dist: networkx>=3.2.1
Requires-Dist: pydantic>=2.11.7
Requires-Dist: questionary>=2.1.0
Requires-Dist: rich>=13.9.4
Requires-Dist: typer>=0.13.0
Provides-Extra: postgresql
Requires-Dist: psycopg[binary]>=3.2.9; extra == "postgresql"
Provides-Extra: openai
Requires-Dist: pydantic-ai-slim[openai]>=0.7.4; extra == "openai"
Provides-Extra: google-genai
Requires-Dist: pydantic-ai-slim[google]>=0.7.4; extra == "google-genai"
Dynamic: license-file
